devnullaas/__init__.py
devnullaas-1.0.0.dist-info/METADATA
devnullaas-1.0.0.dist-info/RECORD
devnullaas-1.0.0.dist-info/WHEEL
devnullaas-1.0.0.dist-info/top_level.txt
