Metadata-Version: 2.1
Name: devnullaas
Version: 1.0.0
Summary: Discard data through devnull-as-a-service.com and other DAAS
Home-page: https://github.com/codl/py-devnullaas
Author: codl
Author-email: codl@codl.fr
License: UNKNOWN
Platform: UNKNOWN
Classifier: Programming Language :: Python :: 3
Classifier: License :: OSI Approved :: BSD License
Classifier: Operating System :: OS Independent
Requires-Dist: requests
